<?xml version="1.0" encoding="utf-8"?>
<savedqueries xmlns:xsi="http://www.w3.org/2001/XMLSchema-instance">
  <savedquery>
    <IsCustomizable>1</IsCustomizable>
    <CanBeDeleted>0</CanBeDeleted>
    <isquickfindquery>0</isquickfindquery>
    <isprivate>0</isprivate>
    <isdefault>1</isdefault>
    <savedqueryid>{78bc71f1-b2c2-48e2-8d9c-38a457548860}</savedqueryid>
    <layoutxml>
      <grid name="csalmpub_approverses" jump="csalmpub_name" select="1" icon="1" preview="1">
        <row name="csalmpub_approvers" id="csalmpub_approversid">
          <cell name="csalmpub_name" width="300" />
          <cell name="createdon" width="125" />
        </row>
      </grid>
    </layoutxml>
    <querytype>2</querytype>
    <fetchxml>
      <fetch version="1.0" mapping="logical">
        <entity name="csalmpub_approvers">
          <attribute name="csalmpub_approversid" />
          <attribute name="csalmpub_name" />
          <attribute name="createdon" />
          <order attribute="csalmpub_name" descending="false" />
          <filter type="and">
            <condition attribute="statecode" operator="eq" value="0" />
          </filter>
        </entity>
      </fetch>
    </fetchxml>
    <IntroducedVersion>1.0</IntroducedVersion>
    <LocalizedNames>
      <LocalizedName description="Approvers Associated View" languagecode="1033" />
    </LocalizedNames>
  </savedquery>
</savedqueries>